Workbook
Name ОстатокНаСтарте: 'Счета и лимиты'!$D$21
Name СвободныйЛимит: 'Счета и лимиты'!$F$36

Sheet Инструкция
B2: Реестр обязательств — исходные данные платёжного календаря
B4: Порядок заполнения
B5: 1. «Счета и лимиты» — остатки по всем расчётным счетам и доступные кредитные лимиты.
B6: 2. «Параметры» — дата начала прогноза и порог тревоги. Остаток подтянется со счетов сам.
B7: 3. «Справочники» — свои объекты и, при необходимости, свои статьи ДДС.
B8: 4. «Реестр» — все ожидаемые поступления и платежи на 13 недель вперёд.
B9: 5. Сохраните файл в папку 01_input и запустите расчёт.
B11: Как заполнять «Реестр»
B12: Одна строка — одно обязательство с одной датой. Платёж частями = несколько строк.
B13: Жёлтые ячейки заполняете вы. Зелёные считаются формулой — их трогать не нужно.
B14: Сумма всегда положительная. Направление задаётся колонкой «Тип».
B15: Тип, Проект, Статья ДДС и Статус выбираются из выпадающего списка.
... B57: Все расчёты в Excel — живыми формулами, значения не вбиваются руками.

Sheet Параметры
B2: Параметры расчёта
B4: Дата начала прогноза | D4: Понедельник первой недели горизонта
B5: Остаток денежных средств на дату начала | C5: ='Счета и лимиты'!$D$21 | D5: Считается как сумма по всем счетам с листа «Счета и лимиты»
B6: Свободные кредитные лимиты | C6: ='Счета и лимиты'!$F$36 | D6: Подушка на случай кассового разрыва, в остаток не входит
B7: Горизонт прогноза, недель | C7: 13 | D7: 13 недель — стандарт казначейского прогноза (квартал)
B8: Порог тревоги, ₽ | D8: Минимальный остаток, ниже которого включается предупреждение
B9: Название компании | D9: Выводится в заголовке отчёта и дашборда
B11: Жёлтые ячейки — для заполнения, зелёные считаются формулой.

Sheet Счета и лимиты
B2: Денежные средства и источники покрытия
B4: Остатки на счетах на дату начала прогноза
B5: Банк | C5: Счёт / назначение | D5: Остаток, ₽ | E5: Комментарий
B21: Итого денежных средств | D21: =SUM(D6:D20)
B24: Кредитные линии и овердрафты
B25: Банк | C25: Вид | D25: Лимит, ₽ | E25: Выбрано, ₽ | F25: Свободно, ₽ | G25: Ставка, % | H25: Действует до | I25: Комментарий
F26: =IF(D26="","",D26-N(E26))
F27: =IF(D27="","",D27-N(E27))
F28: =IF(D28="","",D28-N(E28))
F29: =IF(D29="","",D29-N(E29))
F30: =IF(D30="","",D30-N(E30))
F31: =IF(D31="","",D31-N(E31))
F32: =IF(D32="","",D32-N(E32))
F33: =IF(D33="","",D33-N(E33))
F34: =IF(D34="","",D34-N(E34))
F35: =IF(D35="","",D35-N(E35))
B36: Итого свободный лимит | F36: =SUM(F26:F35)
B38: Свободный лимит не входит в остаток денежных средств. Это источник покрытия разрыва, а не деньги компании.

Sheet Регулярные платежи
A2: Повторяющиеся платежи — описываются правилом, а не строками
A4: Включить | B4: Проект | C4: Контрагент | D4: Основание | E4: Статья ДДС | F4: Сумма, ₽ | G4: Периодичность | H4: День месяца | I4: Действует с | J4: Действует по | K4: Перенос с выходного | L4: Комментарий
A46: Одна строка = правило. Генератор разворачивает его в платежи на весь горизонт.
A47: «День месяца» — число от 1 до 31. Для периодичности «Еженедельно» — день недели (1 = понедельник).
A48: «Перенос с выходного»: Раньше — предыдущий рабочий день (зарплата, аренда); Позже — следующий рабочий день (налоги, проценты).
A49: В «Основании» можно поставить {месяц} — подставится название месяца платежа.
A50: Платежи с меняющейся суммой (налоги, зарплата с премией) вносите в «Реестр» строками.
A51: Нерабочие дни правятся на листе «Справочники».

Sheet Реестр
A1: № | B1: Тип | C1: Проект | D1: Контрагент | E1: Основание | F1: Статья ДДС | G1: Вид деятельности | H1: Сумма, ₽ | I1: Срок платежа | J1: Приоритет | K1: Статус | L1: Комментарий
A2: =IF(D2="","",ROW()-1) | G2: =IF(F2="","",IFERROR(VLOOKUP(F2,Справочники!$A$2:$D$61,4,FALSE),"?")) | J2: =IF(F2="","",IFERROR(IF(N(VLOOKUP(F2,Справочники!$A$2:$D$61,3,FALSE))=0,"",VLOOKUP(F2,Справочники!$A$2:$D$61,3,FALSE)),"?"))
A3: =IF(D3="","",ROW()-1) | G3: =IF(F3="","",IFERROR(VLOOKUP(F3,Справочники!$A$2:$D$61,4,FALSE),"?")) | J3: =IF(F3="","",IFERROR(IF(N(VLOOKUP(F3,Справочники!$A$2:$D$61,3,FALSE))=0,"",VLOOKUP(F3,Справочники!$A$2:$D$61,3,FALSE)),"?"))
A4: =IF(D4="","",ROW()-1) | G4: =IF(F4="","",IFERROR(VLOOKUP(F4,Справочники!$A$2:$D$61,4,FALSE),"?")) | J4: =IF(F4="","",IFERROR(IF(N(VLOOKUP(F4,Справочники!$A$2:$D$61,3,FALSE))=0,"",VLOOKUP(F4,Справочники!$A$2:$D$61,3,FALSE)),"?"))
A5: =IF(D5="","",ROW()-1) | G5: =IF(F5="","",IFERROR(VLOOKUP(F5,Справочники!$A$2:$D$61,4,FALSE),"?")) | J5: =IF(F5="","",IFERROR(IF(N(VLOOKUP(F5,Справочники!$A$2:$D$61,3,FALSE))=0,"",VLOOKUP(F5,Справочники!$A$2:$D$61,3,FALSE)),"?"))
A6: =IF(D6="","",ROW()-1) | G6: =IF(F6="","",IFERROR(VLOOKUP(F6,Справочники!$A$2:$D$61,4,FALSE),"?")) | J6: =IF(F6="","",IFERROR(IF(N(VLOOKUP(F6,Справочники!$A$2:$D$61,3,FALSE))=0,"",VLOOKUP(F6,Справочники!$A$2:$D$61,3,FALSE)),"?"))
A7: =IF(D7="","",ROW()-1) | G7: =IF(F7="","",IFERROR(VLOOKUP(F7,Справочники!$A$2:$D$61,4,FALSE),"?")) | J7: =IF(F7="","",IFERROR(IF(N(VLOOKUP(F7,Справочники!$A$2:$D$61,3,FALSE))=0,"",VLOOKUP(F7,Справочники!$A$2:$D$61,3,FALSE)),"?"))
A8: =IF(D8="","",ROW()-1) | G8: =IF(F8="","",IFERROR(VLOOKUP(F8,Справочники!$A$2:$D$61,4,FALSE),"?")) | J8: =IF(F8="","",IFERROR(IF(N(VLOOKUP(F8,Справочники!$A$2:$D$61,3,FALSE))=0,"",VLOOKUP(F8,Справочники!$A$2:$D$61,3,FALSE)),"?"))
A9: =IF(D9="","",ROW()-1) | G9: =IF(F9="","",IFERROR(VLOOKUP(F9,Справочники!$A$2:$D$61,4,FALSE),"?")) | J9: =IF(F9="","",IFERROR(IF(N(VLOOKUP(F9,Справочники!$A$2:$D$61,3,FALSE))=0,"",VLOOKUP(F9,Справочники!$A$2:$D$61,3,FALSE)),"?"))
A10: =IF(D10="","",ROW()-1) | G10: =IF(F10="","",IFERROR(VLOOKUP(F10,Справочники!$A$2:$D$61,4,FALSE),"?")) | J10: =IF(F10="","",IFERROR(IF(N(VLOOKUP(F10,Справочники!$A$2:$D$61,3,FALSE))=0,"",VLOOKUP(F10,Справочники!$A$2:$D$61,3,FALSE)),"?"))
A11: =IF(D11="","",ROW()-1) | G11: =IF(F11="","",IFERROR(VLOOKUP(F11,Справочники!$A$2:$D$61,4,FALSE),"?")) | J11: =IF(F11="","",IFERROR(IF(N(VLOOKUP(F11,Справочники!$A$2:$D$61,3,FALSE))=0,"",VLOOKUP(F11,Справочники!$A$2:$D$61,3,FALSE)),"?"))
A12: =IF(D12="","",ROW()-1) | G12: =IF(F12="","",IFERROR(VLOOKUP(F12,Справочники!$A$2:$D$61,4,FALSE),"?")) | J12: =IF(F12="","",IFERROR(IF(N(VLOOKUP(F12,Справочники!$A$2:$D$61,3,FALSE))=0,"",VLOOKUP(F12,Справочники!$A$2:$D$61,3,FALSE)),"?"))
A13: =IF(D13="","",ROW()-1) | G13: =IF(F13="","",IFERROR(VLOOKUP(F13,Справочники!$A$2:$D$61,4,FALSE),"?")) | J13: =IF(F13="","",IFERROR(IF(N(VLOOKUP(F13,Справочники!$A$2:$D$61,3,FALSE))=0,"",VLOOKUP(F13,Справочники!$A$2:$D$61,3,FALSE)),"?"))
... A301: =IF(D301="","",ROW()-1) | G301: =IF(F301="","",IFERROR(VLOOKUP(F301,Справочники!$A$2:$D$61,4,FALSE),"?")) | J301: =IF(F301="","",IFERROR(IF(N(VLOOKUP(F301,Справочники!$A$2:$D$61,3,FALSE))=0,"",VLOOKUP(F301,Справочники!$A$2:$D$61,3,FALSE)),"?"))

Sheet Справочники
A1: Статья ДДС | B1: Тип по умолчанию | C1: Приоритет | D1: Вид деятельности | F1: Тип | H1: Статус | J1: Приоритет | K1: Что означает | M1: Вид деятельности | N1: Что входит | P1: Проект | R1: Нерабочие дни
A2: Поступления от заказчиков | B2: Поступление | D2: Операционная | F2: Поступление | H2: План | J2: 1 | K2: Критично — просрочка даёт штрафы и остановку работы | M2: Операционная | N2: Основная деятельность: выручка, зарплата, налоги, материалы, подрядчики | P2: Общие | R2: 46330
A3: Прочие поступления | B3: Поступление | D3: Операционная | F3: Платёж | H3: Подтверждено | J3: 2 | K3: Важно — просрочка портит отношения с контрагентом | M3: Инвестиционная | N3: Покупка и продажа основных средств | R3: 46388
A4: Налоги | B4: Платёж | C4: 1 | D4: Операционная | H4: Оплачено | J4: 3 | K4: Можно перенести без последствий | M4: Финансовая | N4: Кредиты, лизинг, проценты, дивиденды | R4: 46389
A5: ФОТ | B5: Платёж | C5: 1 | D5: Операционная | R5: 46390
A6: Страховые взносы | B6: Платёж | C6: 1 | D6: Операционная | R6: 46391
A7: Подрядчики | B7: Платёж | C7: 2 | D7: Операционная | R7: 46392
A8: Материалы | B8: Платёж | C8: 2 | D8: Операционная | R8: 46393
A9: Аренда | B9: Платёж | C9: 2 | D9: Операционная | R9: 46394
A10: Командировки | B10: Платёж | C10: 3 | D10: Операционная | R10: 46395
A11: Прочие расходы | B11: Платёж | C11: 3 | D11: Операционная | R11: 46441
A12: Покупка оборудования | B12: Платёж | C12: 3 | D12: Инвестиционная | R12: 46454
A13: Продажа активов | B13: Поступление | D13: Инвестиционная | R13: 46508
A14: Получение кредита | B14: Поступление | D14: Финансовая | R14: 46516
A15: Погашение кредита | B15: Платёж | C15: 1 | D15: Финансовая | R15: 46550
A16: Проценты по кредитам | B16: Платёж | C16: 1 | D16: Финансовая | R16: 46695
A17: Лизинг | B17: Платёж | C17: 2 | D17: Финансовая
A18: Дивиденды | B18: Платёж | C18: 3 | D18: Финансовая
P33: Впишите свои объекты
R43: Праздники и перенесённые выходные.
R44: Субботы и воскресенья учитываются автоматически.
R45: Переносы на 2027 год — проверьте по производственному календарю.
A63: Справочник открытый: дописывайте свои статьи, заполняя все четыре колонки
